freshfiles/__init__.py
freshfiles/age.py
freshfiles-0.2.0.dist-info/METADATA
freshfiles-0.2.0.dist-info/WHEEL
freshfiles-0.2.0.dist-info/entry_points.txt
freshfiles-0.2.0.dist-info/RECORD
