Metadata-Version: 2.4
Name: freshfiles
Version: 0.2.0
Summary: Checks if all specified files are fresher (younger) than a given expiry age
Project-URL: homepage, https://github.com/maximehk/freshfiles
Project-URL: repository, https://github.com/maximehk/freshfiles
Author-email: Max <max@noreply.com>
Requires-Python: >=3.12
Requires-Dist: typer>=0.16.0
